chemrxn_cleaner/__init__.py
chemrxn_cleaner/cleaning.py
chemrxn_cleaner/extractor.py
chemrxn_cleaner/filters.py
chemrxn_cleaner/loader.py
chemrxn_cleaner/parsing.py
chemrxn_cleaner/reporting.py
chemrxn_cleaner/types.py
chemrxn_cleaner/utils.py
chemrxn_cleaner-0.0.4.dist-info/licenses/LICENSE
chemrxn_cleaner-0.0.4.dist-info/METADATA
chemrxn_cleaner-0.0.4.dist-info/WHEEL
chemrxn_cleaner-0.0.4.dist-info/top_level.txt
chemrxn_cleaner-0.0.4.dist-info/RECORD
