Metadata-Version: 2.4
Name: chemrxn-cleaner
Version: 0.0.4
Summary: A lightweight toolkit for cleaning and standardizing organic reaction datasets.
Home-page: https://github.com/peiyeliu/chemrxn-cleaner
Author: Peiye Liu
Author-email: Peiye Liu <peiyeliu.work@outlook.com>
License: MIT
Project-URL: Homepage, https://github.com/peiyeliu/chemrxn-cleaner
Classifier: Programming Language :: Python :: 3
Classifier: License :: OSI Approved :: MIT License
Classifier: Intended Audience :: Science/Research
Classifier: Topic :: Scientific/Engineering :: Chemistry
Classifier: Topic :: Scientific/Engineering :: Artificial Intelligence
Requires-Python: >=3.9
License-File: LICENSE
Requires-Dist: rdkit
Requires-Dist: pandas>=1.5.0
Requires-Dist: tqdm>=4.64.0
Requires-Dist: ord-schema>=0.3.0
Provides-Extra: ord
Requires-Dist: ord-schema>=0.3.0; extra == "ord"
Dynamic: author
Dynamic: home-page
Dynamic: license-file
Dynamic: requires-python
